{
  "status": "show",
  "menu_name": "Speed by Ngô Hồng Thái",
  "history_name": "LỊCH SỬ TỔNG",
  "fps_name": "NHTSPEED.IO.VN",
  "auto_name": "Mục tiêu",
  "version": "3.5.2601",
  "update_url": "https://nhtspeed.io.vn/",
  "alert_title": "Thông Báo Từ I AM NHT",
  "update_msg": "Đã có phiên bản mới (v%@).\nHãy cập nhật để có trải nghiệm tốt nhất.",
  "btn_update_now": "Cập nhật ngay",
  "btn_update_later": "Để sau",
  "btn_understood": "Đã hiểu",
  "intro_title": "Chào mừng bạn đến NHTSPEED",
  "intro_version": "Phiên bản %@ | NHTSPEED.IO.VN",
  "intro_loading": "Đang tán zai chờ xíu...",

  "potion_enabled": "on",
  "potion_key_r1": "r1",
  "potion_key_r2": "r2",
  "potion_key_r3": "r3",
  "potion_key_accumulation_bars": "accumulationBarsById",
  "potion_key_currency_full": "generic_currency_expedition_nl_currency",
  "potion_key_currency": "generic_currency",
  "potion_key_reward": "progressive_reward_pr_ec",
  "potion_key_rewards": "genericRewards",
  "potion_key_rewards_alt": "rewards",
  "potion_key_type": "type",
  "potion_key_subtype": "subType",
  "potion_key_status": "status",
  "potion_value_type": "generic_currency",
  "potion_value_subtype": "expedition_nl_currency",
  "potion_value_status": "granted",
  "potion_progress_key_mission": "MissionPoints",
  "potion_progress_key_nonaccumulated": "NonAccumulatedPoints"
}